pyjarowinkler-stubs/__init__.pyi
pyjarowinkler-stubs/distance.pyi
pyjarowinkler_stubs-0.0.1.dist-info/LICENSE
pyjarowinkler_stubs-0.0.1.dist-info/METADATA
pyjarowinkler_stubs-0.0.1.dist-info/WHEEL
pyjarowinkler_stubs-0.0.1.dist-info/top_level.txt
pyjarowinkler_stubs-0.0.1.dist-info/RECORD
