Metadata-Version: 2.1
Name: pyjarowinkler-stubs
Version: 0.0.1
Summary: Stubs for pyjarowinkler package
Author-email: Selvakumar Ravichandran <selvakumar030398@gmail.com>
Project-URL: Homepage, https://github.com/SelvakumarRavichandran98/pyjarowinkler-stubs
Project-URL: Bug Tracker, https://github.com/SelvakumarRavichandran98/pyjarowinkler-stubs/issues
Classifier: Intended Audience :: Developers
Classifier: License :: OSI Approved :: MIT License
Classifier: Operating System :: OS Independent
Classifier: Programming Language :: Python
Classifier: Programming Language :: Python :: 3
Classifier: Programming Language :: Python :: 3.10
Requires-Python: >=3.10
License-File: LICENSE
Provides-Extra: dev
Requires-Dist: autopep8 (~=2.0.1) ; extra == 'dev'
Requires-Dist: flake8 (~=6.0.0) ; extra == 'dev'
Requires-Dist: isort (~=5.10.1) ; extra == 'dev'
Requires-Dist: mypy (~=0.982) ; extra == 'dev'
Requires-Dist: twine (~=4.0.2) ; extra == 'dev'
